core_ct/__init__.py
core_ct/analysis.py
core_ct/core.py
core_ct/importers.py
core_ct/slice.py
core_ct/visualize.py
core_ct-2.0.0.dist-info/LICENSE
core_ct-2.0.0.dist-info/METADATA
core_ct-2.0.0.dist-info/WHEEL
core_ct-2.0.0.dist-info/RECORD
