Metadata-Version: 2.1
Name: core-ct
Version: 2.0.0
Summary: A Python library to assist geologists with the analysis of rock core CT scans
License: MIT
Author: Kira Hanson
Author-email: khanson@mines.edu
Requires-Python: >=3.10,<3.13
Classifier: License :: OSI Approved :: MIT License
Classifier: Programming Language :: Python :: 3
Classifier: Programming Language :: Python :: 3.10
Classifier: Programming Language :: Python :: 3.11
Classifier: Programming Language :: Python :: 3.12
Requires-Dist: ipympl (>=0.9.3,<0.10.0)
Requires-Dist: matplotlib (>=3.8.0,<4.0.0)
Requires-Dist: numpy (>=1.26.0,<2.0.0)
Requires-Dist: pandas (>=2.1.1,<3.0.0)
Requires-Dist: pydicom (>=2.4.3,<3.0.0)
